setup.py
consoleLog.egg-info/PKG-INFO
consoleLog.egg-info/SOURCES.txt
consoleLog.egg-info/dependency_links.txt
consoleLog.egg-info/top_level.txt
src/__init__.py
src/__version__.py
src/consoleLog.py
src/io.py
src/progressBar.py
src/shellColor.py
src/slot.py