Metadata-Version: 1.0
Name: consoleLog
Version: 0.2.4
Summary: Console logger with progress bars and color
Home-page: http://bitbucket.org/lars512/consolelog/
Author: Lars Yencken
Author-email: lljy@csse.unimelb.edu.au
License: BSD
Platform: UNKNOWN
